{
  "methods": [
    {
      "method": "SMA",
      "name": "ma",
      "period": 9
    }
  ],
  "risk": {
    "method": "ATR",
    "atr": {
      "period": 14,
      "multiplier": 1.5
    },
    "percentage": 5,
    "value": 1000
  },
  "positions": [
    {
      "direction": "long",
      "entry": {
        "repeat": "sequence",
        "signal": {
          "filter": "CROSSOVER",
          "signal": "CLOSE",
          "reference": "ma"
        }
      },
      "exit": {
        "signal": {
          "filter": "CROSSUNDER",
          "signal": "CLOSE",
          "reference": "ma"
        }
      },
      "stopLoss": {
        "isTrailing": false
      },
      "takeProfit": {
        "riskMultiplier": 3
      }
    }
  ]
}